pydatalab/__init__.py
pydatalab/backups.py
pydatalab/bokeh_plots.py
pydatalab/config.py
pydatalab/errors.py
pydatalab/feature_flags.py
pydatalab/file_utils.py
pydatalab/logger.py
pydatalab/login.py
pydatalab/main.py
pydatalab/mongo.py
pydatalab/permissions.py
pydatalab/remote_filesystems.py
pydatalab/send_email.py
pydatalab/utils.py
pydatalab/apps/__init__.py
pydatalab/apps/_canary/__init__.py
pydatalab/apps/chat/__init__.py
pydatalab/apps/chat/blocks.py
pydatalab/apps/chat/models.py
pydatalab/apps/echem/__init__.py
pydatalab/apps/echem/blocks.py
pydatalab/apps/echem/utils.py
pydatalab/apps/eis/__init__.py
pydatalab/apps/ftir/__init__.py
pydatalab/apps/nmr/__init__.py
pydatalab/apps/nmr/blocks.py
pydatalab/apps/nmr/utils.py
pydatalab/apps/raman/__init__.py
pydatalab/apps/raman/blocks.py
pydatalab/apps/tga/__init__.py
pydatalab/apps/tga/blocks.py
pydatalab/apps/tga/parsers.py
pydatalab/apps/uvvis/__init__.py
pydatalab/apps/uvvis/utils.py
pydatalab/apps/xrd/__init__.py
pydatalab/apps/xrd/blocks.py
pydatalab/apps/xrd/models.py
pydatalab/apps/xrd/utils.py
pydatalab/blocks/__init__.py
pydatalab/blocks/base.py
pydatalab/blocks/common.py
pydatalab/models/__init__.py
pydatalab/models/blocks.py
pydatalab/models/cells.py
pydatalab/models/collections.py
pydatalab/models/entries.py
pydatalab/models/equipment.py
pydatalab/models/files.py
pydatalab/models/items.py
pydatalab/models/people.py
pydatalab/models/relationships.py
pydatalab/models/samples.py
pydatalab/models/starting_materials.py
pydatalab/models/traits.py
pydatalab/models/utils.py
pydatalab/routes/__init__.py
pydatalab/routes/v0_1/__init__.py
pydatalab/routes/v0_1/_version.py
pydatalab/routes/v0_1/admin.py
pydatalab/routes/v0_1/auth.py
pydatalab/routes/v0_1/blocks.py
pydatalab/routes/v0_1/collections.py
pydatalab/routes/v0_1/files.py
pydatalab/routes/v0_1/graphs.py
pydatalab/routes/v0_1/healthcheck.py
pydatalab/routes/v0_1/info.py
pydatalab/routes/v0_1/items.py
pydatalab/routes/v0_1/remotes.py
datalab_server-0.6.7.dist-info/METADATA
datalab_server-0.6.7.dist-info/WHEEL
datalab_server-0.6.7.dist-info/top_level.txt
datalab_server-0.6.7.dist-info/RECORD
