Metadata-Version: 2.4
Name: datalab-server
Version: 0.6.7
Summary: datalab is a research data management platform for materials science and chemistry.
Author-email: datalab development team <dev@datalab-org.io>
License-Expression: MIT
Project-URL: homepage, https://github.com/datalab-org/datalab
Project-URL: repository, https://github.com/datalab-org/datalab
Project-URL: documentation, https://docs.datalab-org.io
Project-URL: changelog, https://github.com/datalab-org/datalab/releases
Keywords: research data management,materials,chemistry
Classifier: Programming Language :: Python :: 3
Classifier: Programming Language :: Python :: 3.10
Classifier: Programming Language :: Python :: 3.11
Classifier: Intended Audience :: Science/Research
Classifier: Intended Audience :: Information Technology
Classifier: Topic :: Scientific/Engineering
Requires-Python: <3.12,>=3.10
Requires-Dist: bokeh<3.0,~=2.4
Requires-Dist: matplotlib~=3.8
Requires-Dist: periodictable~=1.7
Requires-Dist: pydantic[dotenv,email]<2.0
Requires-Dist: pint~=0.24
Requires-Dist: pandas[excel]~=2.2
Requires-Dist: pymongo~=4.7
Provides-Extra: server
Requires-Dist: Flask~=3.0; extra == "server"
Requires-Dist: Flask-Login~=0.6; extra == "server"
Requires-Dist: Flask-Cors~=6.0; extra == "server"
Requires-Dist: Flask-Dance~=7.1; extra == "server"
Requires-Dist: Flask-PyMongo~=2.3; extra == "server"
Requires-Dist: Flask-Mail~=0.10; extra == "server"
Requires-Dist: Flask-Compress~=1.15; extra == "server"
Requires-Dist: Werkzeug~=3.0; extra == "server"
Requires-Dist: python-dotenv~=1.0; extra == "server"
Requires-Dist: pillow~=11.0; extra == "server"
Requires-Dist: pyjwt~=2.9; extra == "server"
Requires-Dist: invoke~=2.2; extra == "server"
Provides-Extra: apps
Requires-Dist: scipy~=1.13; extra == "apps"
Requires-Dist: nmrglue~=0.10; extra == "apps"
Requires-Dist: navani>=0.1.13; extra == "apps"
Requires-Dist: pybaselines~=1.1; extra == "apps"
Requires-Dist: renishawwire>=0.1.16; extra == "apps"
Requires-Dist: python-dateutil~=2.9; extra == "apps"
Requires-Dist: matador-db>=0.11.2; extra == "apps"
Requires-Dist: psutil>=7.0.0; extra == "apps"
Provides-Extra: app-plugins-git
Requires-Dist: datalab-app-plugin-insitu; extra == "app-plugins-git"
Provides-Extra: chat
Requires-Dist: langchain<0.3,>=0.2.6; extra == "chat"
Requires-Dist: langchain-openai~=0.1; extra == "chat"
Requires-Dist: langchain-anthropic~=0.1; extra == "chat"
Requires-Dist: tiktoken~=0.7; extra == "chat"
Requires-Dist: transformers~=4.42; extra == "chat"
Provides-Extra: deploy
Requires-Dist: gunicorn~=23.0; extra == "deploy"
Provides-Extra: all
Requires-Dist: datalab-server[apps,chat,server]; extra == "all"
